README.md
setup.py
minipipe/__init__.py
minipipe/base.py
minipipe/pipelines.py
minipipe/pipes.py
minipipe.egg-info/PKG-INFO
minipipe.egg-info/SOURCES.txt
minipipe.egg-info/dependency_links.txt
minipipe.egg-info/not-zip-safe
minipipe.egg-info/requires.txt
minipipe.egg-info/top_level.txt