Metadata-Version: 2.1
Name: minipipe
Version: 0.1.9
Summary: A machine learning mini-batch pipeline for out-of-memory training
Home-page: https://minipipe.readthedocs.io
Author: James D. Pearce
Author-email: jdp.pearce@gmail.com
License: MIT
Platform: UNKNOWN
Classifier: Programming Language :: Python :: 3
Classifier: License :: OSI Approved :: MIT License
Classifier: Operating System :: OS Independent
